{"Stack": {
  "Name":"cyl3x2_100and70_aa",
  "Layers":150,
  "Width":500,
  "Height":300,
  "Antialias":"True"
  },
  "Primitives":[
    {
      "Type":"Ellipse",
      "D":"29",
      "Cy":100,

      "Start":0,
      "End":"150",
      "Color":"rgb(255,255,255)"
    },
    {
      "Type":"Ellipse",
      "D":"29",
      "Cx":150,
      "Cy":100,
      "Start":0,
      "End":"150",
      "Color":"rgb(255,255,255)"
    },
    {
      "Type":"Ellipse",
      "D":"29",
      "Cx":350,
      "Cy":100,
      "Start":0,
      "End":"150",
      "Color":"rgb(255,255,255)"
    },
    {
      "Type":"Ellipse",
      "D":"36",
      "Cy":200,
      "Start":0,
      "End":"150",
      "Color":"rgb(178,178,178)"
    },
    {
      "Type":"Ellipse",
      "D":"36",
      "Cy":200,
      "Cx":150,
      "Start":0,
      "End":"150",
      "Color":"rgb(178,178,178)"
    },
    {
      "Type":"Ellipse",
      "D":"36",
      "Cy":200,
      "Cx":350,
      "Start":0,
      "End":"150",
      "Color":"rgb(178,178,178)"
    }
  ]
}